PRIMO_DHS_20DEC21/__init__.py
PRIMO_DHS_20DEC21-1.0.dist-info/LICENSE
PRIMO_DHS_20DEC21-1.0.dist-info/METADATA
PRIMO_DHS_20DEC21-1.0.dist-info/WHEEL
PRIMO_DHS_20DEC21-1.0.dist-info/top_level.txt
PRIMO_DHS_20DEC21-1.0.dist-info/RECORD
