Metadata-Version: 2.1
Name: PRIMO-DHS-20DEC21
Version: 1.0
Summary: A tool to list prime numbers
Home-page: UNKNOWN
Author: Diego Higeo
Author-email: Diegohigeo@gmail.com
License: GNU GPLv3
Keywords: prime numbers
Platform: UNKNOWN
Classifier: Development Status :: 4 - Beta
Classifier: Intended Audience :: Developers
Classifier: Topic :: Utilities
Classifier: License :: OSI Approved :: GNU General Public License v3 (GPLv3)
Classifier: Programming Language :: Python :: 3
Classifier: Operating System :: OS Independent
License-File: LICENSE
